{
  "hotel": [
    {
      "name": "ananya",
      "age": "23",
      "city": "bhopal",
      "aadhar": "9874943209i0",
      "number": "8085212206",
      "person": "1",
      "fees": 2000,
      "id": "d225"
    },
    {
      "id": "658e",
      "name": "viplove sana",
      "age": "23",
      "city": "bhopal",
      "aadhar": "9874943209i0",
      "number": "8085212206",
      "person": "",
      "fees": 2000
    },
    {
      "id": "d26e",
      "name": "viplove sana",
      "age": "23",
      "city": "bhopal",
      "aadhar": "9874943209i0",
      "number": "8085212206",
      "person": "2",
      "fees": 2000
    },
    {
      "name": "faraz ahmed",
      "age": "27",
      "city": "bhopal",
      "aadhar": "9874943209i0",
      "number": "86727348786",
      "person": "1",
      "fees": 2000,
      "id": "0934"
    },
    {
      "id": "59be",
      "name": "viplove sana",
      "age": "23",
      "city": "bhopal",
      "aadhar": "9874943209i0",
      "number": "8085212206",
      "person": "3",
      "fees": 2000
    },
    {
      "id": "c0a2",
      "name": "viplove sana",
      "age": "23",
      "city": "bhopal",
      "aadhar": "9874943209i0",
      "number": "8085212206",
      "person": "3",
      "fees": 2000
    },
    {
      "id": "f948",
      "name": "viplove sana",
      "age": "23",
      "city": "bhopal",
      "aadhar": "9874943209i0",
      "number": "8085212206",
      "person": "3",
      "fees": 2000
    },
    {
      "id": "7a83",
      "name": "viplove sana",
      "age": "23",
      "city": "bhopal",
      "aadhar": "9874943209i0",
      "number": "8085212206",
      "person": "1",
      "fees": 2000
    },
    {
      "id": "3b30",
      "name": "viplove sana",
      "age": "23",
      "city": "bhopal",
      "aadhar": "9874943209i0",
      "number": "8085212206",
      "person": "2",
      "fees": 2000
    },
    {
      "id": "ec2a",
      "name": "viplove sana",
      "age": "23",
      "city": "bhopal",
      "aadhar": "9874943209i0",
      "number": "8085212206",
      "person": "2",
      "fees": 2000
    },
    {
      "id": "4c1d",
      "name": "viplove sana",
      "age": "23",
      "city": "bhopal",
      "aadhar": "9874943209i0",
      "number": "8085212206",
      "person": "1",
      "fees": 2000
    },
    {
      "id": "3595",
      "name": "Ashmita thakur",
      "age": "21",
      "city": "bhopal",
      "aadhar": "878998298290",
      "number": "799282982",
      "person": "1",
      "fees": 2000
    }
  ]
}